{
    "11213963074299515130": [
        [
            4209588,
            "_start"
        ]
    ],
    "4213952": [
        [
            4235499,
            "safe_hasher"
        ]
    ],
    "4226256": [
        [
            4235499,
            "safe_hasher"
        ]
    ],
    "4226240": [
        [
            4235499,
            "safe_hasher"
        ]
    ],
    "4226208": [
        [
            4235587,
            "hash_find_entry"
        ],
        [
            4235675,
            "hash_find_entry"
        ]
    ],
    "4225408": [
        [
            4238275,
            "hash_free"
        ]
    ]
}